{
  "meta": {
    "source": "CCDA",
    "generated_on": "2026-01-15",
    "language": "en"
  },
  "patient": {
    "nickname": "Maa",
    "age_range": "70s",
    "sex": "F",
    "conditions_display": ["Diabetes", "High blood pressure", "Kidney issues"]
  },
  "medications": [
    {
      "medication_name": "Metformin",
      "sig_text": "Take 1 tablet by mouth twice daily with meals",
      "dose": "500 mg",
      "route": "PO",
      "frequency": "BID",
      "timing": "morning and evening, with food",
      "status": "Active",
      "clinician_notes": "Take with food to reduce stomach upset",
      "interaction_notes": ""
    },
    {
      "medication_name": "Insulin glargine",
      "sig_text": "Inject subcutaneously once daily at bedtime",
      "dose": "10 units",
      "route": "SubQ",
      "frequency": "Daily",
      "timing": "at bedtime",
      "status": "Active",
      "clinician_notes": "Store in refrigerator. Do not freeze.",
      "interaction_notes": ""
    },
    {
      "medication_name": "Lisinopril",
      "sig_text": "Take 1 tablet by mouth daily",
      "dose": "10 mg",
      "route": "PO",
      "frequency": "Daily",
      "timing": "",
      "status": "Active",
      "clinician_notes": "",
      "interaction_notes": ""
    },
    {
      "medication_name": "Furosemide",
      "sig_text": "Take 1 tablet by mouth daily in the morning",
      "dose": "20 mg",
      "route": "PO",
      "frequency": "Daily",
      "timing": "morning",
      "status": "Active",
      "clinician_notes": "",
      "interaction_notes": ""
    },
    {
      "medication_name": "Atorvastatin",
      "sig_text": "Take 1 tablet by mouth daily at bedtime",
      "dose": "20 mg",
      "route": "PO",
      "frequency": "Daily",
      "timing": "at bedtime",
      "status": "Active",
      "clinician_notes": "",
      "interaction_notes": ""
    },
    {
      "medication_name": "Aspirin",
      "sig_text": "Take 1 tablet by mouth daily",
      "dose": "81 mg",
      "route": "PO",
      "frequency": "Daily",
      "timing": "",
      "status": "Active",
      "clinician_notes": "",
      "interaction_notes": ""
    },
    {
      "medication_name": "Levothyroxine",
      "sig_text": "Take 1 tablet by mouth daily on empty stomach",
      "dose": "50 mcg",
      "route": "PO",
      "frequency": "Daily",
      "timing": "morning, 30-60 minutes before breakfast",
      "status": "Active",
      "clinician_notes": "Take on empty stomach. Separate from calcium and iron by 4 hours.",
      "interaction_notes": ""
    },
    {
      "medication_name": "Omeprazole",
      "sig_text": "Take 1 capsule by mouth daily before breakfast",
      "dose": "20 mg",
      "route": "PO",
      "frequency": "Daily",
      "timing": "",
      "status": "Active",
      "clinician_notes": "",
      "interaction_notes": ""
    }
  ],
  "results": [
    {
      "test_name": "Hemoglobin A1c",
      "meaning_category": "Needs follow-up",
      "flag": "high",
      "result_date": "2026-01-05",
      "source_note": "Above target range"
    },
    {
      "test_name": "Kidney function (eGFR)",
      "meaning_category": "Slightly off",
      "flag": "low",
      "result_date": "2026-01-05",
      "source_note": "Mild decrease noted"
    },
    {
      "test_name": "Cholesterol panel",
      "meaning_category": "Normal",
      "flag": "normal",
      "result_date": "2026-01-05",
      "source_note": "LDL within goal"
    }
  ],
  "care_gaps": [
    {
      "item_text": "Eye exam overdue",
      "next_step": "Call clinic to schedule diabetic eye exam",
      "time_bucket": "This Week",
      "source": "Health Maintenance"
    },
    {
      "item_text": "A1c lab due",
      "next_step": "Schedule lab visit",
      "time_bucket": "Today",
      "source": "After Visit Summary"
    },
    {
      "item_text": "Follow-up appointment",
      "next_step": "Call clinic to schedule",
      "time_bucket": "This Week",
      "source": "After Visit Summary"
    },
    {
      "item_text": "Flu shot recommended",
      "next_step": "Ask pharmacy about availability",
      "time_bucket": "Later",
      "source": "Health Maintenance"
    }
  ],
  "contacts": {
    "clinic_name": "Riverside Primary Care",
    "clinic_phone": "555-0100",
    "pharmacy_name": "Main Street Pharmacy",
    "pharmacy_phone": "555-0199",
    "pharmacy_address": "123 Main St, Riverdale, CA"
  }
}
